LICENSE
MANIFEST.in
VARIABLES.JSON
setup.py
RHYTHMS.egg-info/PKG-INFO
RHYTHMS.egg-info/SOURCES.txt
RHYTHMS.egg-info/dependency_links.txt
RHYTHMS.egg-info/requires.txt
RHYTHMS.egg-info/top_level.txt
SOURCE/MODULES/RHYTHMS/RHYTHM.PROCESS.py
SOURCE/MODULES/RHYTHMS/__init__.py
SOURCE/MODULES/RHYTHMS/PROCESS/START.PROCESS.py