Metadata-Version: 2.1
Name: RHYTHMS
Version: 0.0.6
License: LL
License-File: LICENSE
Requires-Dist: click
Requires-Dist: rethinkdb
